paper_hive/__init__.py
paper_hive/agent.py
paper_hive/paper_fetcher.py
paper_hive-0.0.1.dist-info/LICENSE
paper_hive-0.0.1.dist-info/METADATA
paper_hive-0.0.1.dist-info/WHEEL
paper_hive-0.0.1.dist-info/RECORD
